CHANGELOG.TXT
MANIFEST.in
README.md
ez_setup.py
requirements.txt
setup.cfg
setup.py
avrtsb/__init__.py
avrtsb/firmware.py
avrtsb/pytsb.py
avrtsb/setup_locale.py
avrtsb/tsb_db.pklz
avrtsb/tsb_locale.py
avrtsb/tsbloader.py
avrtsb.egg-info/PKG-INFO
avrtsb.egg-info/SOURCES.txt
avrtsb.egg-info/dependency_links.txt
avrtsb.egg-info/entry_points.txt
avrtsb.egg-info/not-zip-safe
avrtsb.egg-info/requires.txt
avrtsb.egg-info/top_level.txt
avrtsb/locale/pytsb.pot
avrtsb/locale/cs_CZ/LC_MESSAGES/pytsb.mo
avrtsb/locale/cs_CZ/LC_MESSAGES/pytsb.po
avrtsb/locale/en_US/LC_MESSAGES/pytsb.mo
avrtsb/locale/en_US/LC_MESSAGES/pytsb.po
avrtsb/locale/zh_TW/LC_MESSAGES/pytsb.mo
avrtsb/locale/zh_TW/LC_MESSAGES/pytsb.po
scripts/tsb_compile.py