Metadata-Version: 1.2
Name: avrtsb
Version: 0.2.6
Summary: Python version of TinySafeBootA tiny and safe Bootloader for AVR-ATtinys and ATmegas
Home-page: http://github.com/mvyskoc/avrtsb
Author: Martin Vyskočil
Author-email: m.vyskoc@seznam.cz
License: GPLv3
Download-URL: https://github.com/mvyskoc/avrtsb/tarball/v0.2.6
Keywords: TinySafeBoot,AVR,bootloader
Platform: UNKNOWN
Classifier: Development Status :: 3 - Alpha
Classifier: Environment :: Console
Classifier: Intended Audience :: Developers
Classifier: Programming Language :: Python
Classifier: Programming Language :: Python :: 2
Classifier: Topic :: Software Development :: Embedded Systems
Classifier: License :: OSI Approved :: GNU General Public License v3 (GPLv3)
Requires-Python: ~=2.5
